{"api":{"dashboards":[{"id":1,"label":"Dashboard 1"},{"id":2,"label":"Dashboard 2"},{"id":3,"label":"Dashboard 3"},{"id":4,"label":"Dashboard 4"},{"id":5,"label":"Dashboard 5"},{"id":6,"label":"Dashboard 6"},{"id":7,"label":"Dashboard 7"},{"id":8,"label":"Dashboard 8"},{"id":9,"label":"Dashboard 9"},{"id":10,"label":"Dashboard 10"}],"widgets":[{"id":1,"dashboardId":1,"label":"Widget 1"},{"id":2,"dashboardId":1,"label":"Widget 2"},{"id":3,"dashboardId":1,"label":"Widget 3"},{"id":4,"dashboardId":1,"label":"Widget 4"},{"id":5,"dashboardId":1,"label":"Widget 5"},{"id":6,"dashboardId":1,"label":"Widget 6"},{"id":7,"dashboardId":1,"label":"Widget 7"},{"id":8,"dashboardId":1,"label":"Widget 8"},{"id":9,"dashboardId":1,"label":"Widget 9"},{"id":10,"dashboardId":1,"label":"Widget 10"},{"id":11,"dashboardId":2,"label":"Widget 11"},{"id":12,"dashboardId":2,"label":"Widget 12"},{"id":13,"dashboardId":2,"label":"Widget 13"},{"id":14,"dashboardId":2,"label":"Widget 14"},{"id":15,"dashboardId":2,"label":"Widget 15"},{"id":16,"dashboardId":2,"label":"Widget 16"},{"id":17,"dashboardId":2,"label":"Widget 17"},{"id":18,"dashboardId":2,"label":"Widget 18"},{"id":19,"dashboardId":2,"label":"Widget 19"},{"id":20,"dashboardId":2,"label":"Widget 20"},{"id":21,"dashboardId":3,"label":"Widget 21"},{"id":22,"dashboardId":3,"label":"Widget 22"},{"id":23,"dashboardId":3,"label":"Widget 23"},{"id":24,"dashboardId":3,"label":"Widget 24"},{"id":25,"dashboardId":3,"label":"Widget 25"},{"id":26,"dashboardId":3,"label":"Widget 26"},{"id":27,"dashboardId":3,"label":"Widget 27"},{"id":28,"dashboardId":3,"label":"Widget 28"},{"id":29,"dashboardId":3,"label":"Widget 29"},{"id":30,"dashboardId":3,"label":"Widget 30"},{"id":31,"dashboardId":4,"label":"Widget 31"},{"id":32,"dashboardId":4,"label":"Widget 32"},{"id":33,"dashboardId":4,"label":"Widget 33"},{"id":34,"dashboardId":4,"label":"Widget 34"},{"id":35,"dashboardId":4,"label":"Widget 35"},{"id":36,"dashboardId":4,"label":"Widget 36"},{"id":37,"dashboardId":4,"label":"Widget 37"},{"id":38,"dashboardId":4,"label":"Widget 38"},{"id":39,"dashboardId":4,"label":"Widget 39"},{"id":40,"dashboardId":4,"label":"Widget 40"},{"id":41,"dashboardId":5,"label":"Widget 41"},{"id":42,"dashboardId":5,"label":"Widget 42"},{"id":43,"dashboardId":5,"label":"Widget 43"},{"id":44,"dashboardId":5,"label":"Widget 44"},{"id":45,"dashboardId":5,"label":"Widget 45"},{"id":46,"dashboardId":5,"label":"Widget 46"},{"id":47,"dashboardId":5,"label":"Widget 47"},{"id":48,"dashboardId":5,"label":"Widget 48"},{"id":49,"dashboardId":5,"label":"Widget 49"},{"id":50,"dashboardId":5,"label":"Widget 50"},{"id":51,"dashboardId":6,"label":"Widget 51"},{"id":52,"dashboardId":6,"label":"Widget 52"},{"id":53,"dashboardId":6,"label":"Widget 53"},{"id":54,"dashboardId":6,"label":"Widget 54"},{"id":55,"dashboardId":6,"label":"Widget 55"},{"id":56,"dashboardId":6,"label":"Widget 56"},{"id":57,"dashboardId":6,"label":"Widget 57"},{"id":58,"dashboardId":6,"label":"Widget 58"},{"id":59,"dashboardId":6,"label":"Widget 59"},{"id":60,"dashboardId":6,"label":"Widget 60"},{"id":61,"dashboardId":7,"label":"Widget 61"},{"id":62,"dashboardId":7,"label":"Widget 62"},{"id":63,"dashboardId":7,"label":"Widget 63"},{"id":64,"dashboardId":7,"label":"Widget 64"},{"id":65,"dashboardId":7,"label":"Widget 65"},{"id":66,"dashboardId":7,"label":"Widget 66"},{"id":67,"dashboardId":7,"label":"Widget 67"},{"id":68,"dashboardId":7,"label":"Widget 68"},{"id":69,"dashboardId":7,"label":"Widget 69"},{"id":70,"dashboardId":7,"label":"Widget 70"},{"id":71,"dashboardId":8,"label":"Widget 71"},{"id":72,"dashboardId":8,"label":"Widget 72"},{"id":73,"dashboardId":8,"label":"Widget 73"},{"id":74,"dashboardId":8,"label":"Widget 74"},{"id":75,"dashboardId":8,"label":"Widget 75"},{"id":76,"dashboardId":8,"label":"Widget 76"},{"id":77,"dashboardId":8,"label":"Widget 77"},{"id":78,"dashboardId":8,"label":"Widget 78"},{"id":79,"dashboardId":8,"label":"Widget 79"},{"id":80,"dashboardId":8,"label":"Widget 80"},{"id":81,"dashboardId":9,"label":"Widget 81"},{"id":82,"dashboardId":9,"label":"Widget 82"},{"id":83,"dashboardId":9,"label":"Widget 83"},{"id":84,"dashboardId":9,"label":"Widget 84"},{"id":85,"dashboardId":9,"label":"Widget 85"},{"id":86,"dashboardId":9,"label":"Widget 86"},{"id":87,"dashboardId":9,"label":"Widget 87"},{"id":88,"dashboardId":9,"label":"Widget 88"},{"id":89,"dashboardId":9,"label":"Widget 89"},{"id":90,"dashboardId":9,"label":"Widget 90"},{"id":91,"dashboardId":10,"label":"Widget 91"},{"id":92,"dashboardId":10,"label":"Widget 92"},{"id":93,"dashboardId":10,"label":"Widget 93"},{"id":94,"dashboardId":10,"label":"Widget 94"},{"id":95,"dashboardId":10,"label":"Widget 95"},{"id":96,"dashboardId":10,"label":"Widget 96"},{"id":97,"dashboardId":10,"label":"Widget 97"},{"id":98,"dashboardId":10,"label":"Widget 98"},{"id":99,"dashboardId":10,"label":"Widget 99"},{"id":100,"dashboardId":10,"label":"Widget 100"}],"charts":[{"id":1,"data":[["Nedra Bogisich",13],["Laisha Walker",33],["Chauncey Powlowski",40],["Chelsie McClure",39],["Marcel Collins",23],["Eulalia Sporer",6],["Antwon King",39]]},{"id":2,"data":[["Sim Fisher",27],["Irma Hackett",17],["Jonatan Collier",30],["Dalton Rath",49],["Mrs. Darrick Bayer",20],["Elissa Brekke I",24],["Kendrick Nikolaus",8]]},{"id":3,"data":[["Ansley Goldner",39],["Ms. Zola Wunsch",6],["Carley Corwin",31],["Mrs. Forrest McGlynn",32],["Willa Fay",38],["Miss Hadley Kshlerin",41],["Catharine Dibbert",50]]},{"id":4,"data":[["Grady Rippin",47],["Izaiah Morar DVM",8],["Bertrand Lueilwitz",9],["Helene Kulas",21],["Jo Lesch",21],["Maynard Wisozk",9],["Wilfrid Schmeler",45]]},{"id":5,"data":[["Casandra Satterfield",16],["Johnathan Hodkiewicz",32],["Dawn Halvorson",29],["Ms. Felicia Fritsch",28],["Camden Windler",24],["Susana Effertz",42],["Velda Bradtke",35]]},{"id":6,"data":[["Javonte Quitzon",29],["Javon Lowe",40],["Jana Langosh",28],["Dayton Davis",34],["Amy O'Conner",30],["Payton Schultz",34],["Marcellus Lockman V",42]]},{"id":7,"data":[["Chanelle O'Keefe",38],["Miss Mckenzie Kohler",21],["Rossie Gorczany",46],["Frederick Bashirian",49],["Lenora Halvorson",31],["Santina McCullough",29],["Thora Boyer",5]]},{"id":8,"data":[["Fatima Dare",22],["Addison Cole",32],["Dr. Astrid Weber",15],["Elda Dach Jr.",19],["Cyrus Kuhlman",50],["Paula Brown III",23],["Constance Nitzsche",38]]},{"id":9,"data":[["Vicenta Dare",37],["Mr. Norval Maggio",16],["Kayla Turcotte",8],["Esta Hoeger",39],["Lyda McKenzie",7],["Al Daugherty",50],["Shad Schaefer",30]]},{"id":10,"data":[["Heber Schinner",20],["Chanelle Russel",6],["Makenna Robel",7],["Trey Sauer",14],["Eldridge Greenholt",49],["Jarret Schuppe",21],["Cristobal Steuber",32]]},{"id":11,"data":[["Manuel Lind",41],["Clint Jakubowski I",36],["Aletha Abbott",47],["Eryn Reichert DVM",8],["Greg Bruen",39],["Ally Corkery",29],["Rosina Mann",38]]},{"id":12,"data":[["Kyla Keebler IV",10],["Anjali Hodkiewicz",19],["Mr. Meghan Hamill",6],["Jared Schinner",40],["Fernando Waters",37],["Shanie Reilly",12],["Zella Predovic",32]]},{"id":13,"data":[["Quentin Mills",17],["Isaiah Walker",5],["Ernest Shanahan",24],["Jazmin Ziemann",14],["Raymundo Herman",24],["Maymie Thiel",14],["Jamey Schaden",17]]},{"id":14,"data":[["Bonita Kilback",44],["Miss Dock Becker",28],["Mrs. Leilani Kirlin",35],["Tad Dach",24],["Luciano Hansen",18],["Adrianna Crist",49],["Melyna Kunde PhD",38]]},{"id":15,"data":[["Garett Ebert",5],["Cade Hauck",32],["Kyle Kuvalis",47],["Chad Champlin",47],["Autumn Bogan",45],["Guy Glover",8],["Georgette Kshlerin",6]]},{"id":16,"data":[["Colton Grimes",34],["Deven Huel",8],["Petra Gerhold",34],["Fredy Rowe",16],["Ottis West",20],["Frankie Legros",27],["Ms. London Haag",6]]},{"id":17,"data":[["Mrs. Zachary Zboncak",31],["Terrance Watsica",11],["Devante Langworth DDS",12],["Mrs. Marilou McKenzie",12],["Wilhelmine Medhurst",48],["Orion Hermiston",34],["Ole McDermott V",35]]},{"id":18,"data":[["Dr. Kaylin Weimann",6],["Clotilde Koss",40],["Jesus Abbott",47],["Marisa Pagac",25],["Andreanne Franecki",12],["Robert Stark",34],["Michelle Cruickshank",29]]},{"id":19,"data":[["Shyann Doyle",12],["Dr. Briana Barrows",39],["Carol Gutmann",31],["Richard Wisozk",33],["Kaleigh Schaden",36],["Naomie Carter",14],["Mrs. Layne Little",23]]},{"id":20,"data":[["Rey Parker",48],["Rosalee Cartwright",20],["Leopold Emard",33],["Rey McDermott",20],["Ernie Gulgowski",29],["Hermann Dicki",27],["Demarcus Berge",8]]},{"id":21,"data":[["Thaddeus McGlynn",49],["Garrett Emmerich",28],["Liana Ferry",16],["Mr. Tressa Farrell",47],["Rosemarie Wuckert",25],["Dr. Evan Yundt",8],["Alden Larson",45]]},{"id":22,"data":[["Markus Lynch",41],["Jaydon Cruickshank",18],["Vida Altenwerth DVM",45],["Ms. Casandra Renner",49],["Vance Stoltenberg DVM",29],["Agustina Olson",14],["Roberta Tremblay",13]]},{"id":23,"data":[["Mrs. Alize Rice",48],["Miss Marco Halvorson",13],["Orlo Stanton Jr.",18],["Esther Breitenberg",27],["Mayra Corwin",42],["Julianne Lubowitz",42],["Bettye Nikolaus",23]]},{"id":24,"data":[["Ima Batz",27],["Lester Kerluke",37],["Miss Ambrose Larson",19],["Marta Beer",43],["Avery Macejkovic",46],["Nat Hilll",24],["Jimmy Greenfelder",39]]},{"id":25,"data":[["Kaleigh Ankunding",37],["Christophe Fadel",15],["Mr. Garrison Tromp",44],["Tatum Reynolds",7],["Jayde Botsford Jr.",13],["Monte Weimann",41],["Efrain Labadie",33]]},{"id":26,"data":[["Bertrand Lemke",24],["Katlynn VonRueden",8],["Amani Sipes",48],["Harmon Hyatt",46],["Rubie Kiehn",18],["August Rippin",16],["Ron Sauer",26]]},{"id":27,"data":[["Dashawn Hickle",27],["Quinten Nader",42],["Fletcher McClure",27],["Ms. Athena Dooley",39],["Abdullah Stroman III",44],["Dallas Lakin PhD",15],["Chaya Hane",30]]},{"id":28,"data":[["Desmond Marvin",13],["Coralie Spencer Sr.",43],["Alexa Bernhard",9],["Oceane Hagenes",9],["Kassandra Kilback",47],["Mr. Nico Tremblay",42],["Lavina West",20]]},{"id":29,"data":[["Ayden Effertz",9],["Brandi Towne",31],["Lilly Bayer",25],["Lois Skiles",5],["Ella Armstrong",41],["Madaline Bosco",41],["Dr. Reba Greenholt",34]]},{"id":30,"data":[["Dr. Meredith Weber",23],["Tyrique Abbott",12],["Ole Kertzmann V",50],["Queenie Roob III",38],["Felicity Labadie",37],["Adella Block",15],["Melba Hessel",12]]},{"id":31,"data":[["Braulio Powlowski",24],["Dr. Pamela Morissette",23],["Wendell Collins",38],["Joanny Gottlieb",11],["Fanny Lang",49],["Delaney Rippin",45],["Elisha Kuhic",8]]},{"id":32,"data":[["Ressie Graham",41],["Mallie O'Hara",12],["Mertie Mills",10],["Cristobal Kemmer",14],["Yazmin Casper",21],["Dell Ledner",48],["Oda Fisher",42]]},{"id":33,"data":[["Americo Mohr",27],["Kamren Grimes",39],["Phoebe Klein",31],["Kamren Steuber II",8],["Mrs. Nestor Satterfield",15],["Guido Vandervort",33],["Earline Runte",15]]},{"id":34,"data":[["Weston Cremin",49],["Mrs. Haylie Botsford",36],["Zachary Jenkins",19],["Jacinto Bogisich",13],["Miss Scot Goyette",27],["Dallas O'Reilly",21],["Mr. Brooke Mayert",28]]},{"id":35,"data":[["Adrian Balistreri DDS",8],["Candida Homenick",36],["Emilia Reichel",37],["Tristian Schmeler",38],["Kamille Wilderman",16],["Mrs. Taylor Cole",27],["Jarod Gislason",44]]},{"id":36,"data":[["Daniella Windler",27],["Hester Ankunding",7],["Eloy Roberts",39],["Vickie Abernathy",22],["Ismael Kemmer",28],["Shania Simonis",46],["London Haley",31]]},{"id":37,"data":[["Dr. Dale Schamberger",26],["Judy Kerluke",27],["Jensen Graham",35],["Stephania Runte",23],["Litzy Harber",16],["Alycia Carter",33],["Zoe Hagenes",38]]},{"id":38,"data":[["Jeromy Bartell DVM",29],["Lesley Murazik III",32],["Carol Krajcik",14],["Eveline Kuvalis",23],["Creola Wiegand",17],["Sylvia Ritchie",5],["Weston Gorczany",21]]},{"id":39,"data":[["Hugh Hermiston",14],["Serena Monahan",20],["Miss Moses Friesen",37],["Matilda Hayes",22],["Terrill Koch V",25],["Emilio Prohaska",30],["Chester Swift",15]]},{"id":40,"data":[["Mrs. Gaston Kovacek",37],["Ignatius Kuhic",18],["Germaine Treutel IV",33],["Evans Kessler",23],["Dawn Marvin",6],["Mrs. Halie Marvin",40],["Emma Parker",10]]},{"id":41,"data":[["Lynn Beier",28],["Carrie Waters",40],["Brendan Marks",20],["Richard Haag II",17],["Walter Russel",22],["Uriah Beer II",11],["Makenzie Bayer",28]]},{"id":42,"data":[["Carey Nicolas",25],["Vincenza Gleichner",45],["Ms. Wilhelmine Sauer",49],["Odell Hamill",27],["Destin Schroeder",36],["Garrison Lindgren",32],["Ms. Ethyl Fisher",35]]},{"id":43,"data":[["Theo Strosin",13],["Melba Marvin",35],["Agnes Bradtke",14],["Brionna Swaniawski",24],["Brittany Ruecker",35],["Jabari Johnston",30],["Destiny O'Keefe",43]]},{"id":44,"data":[["Rowan Pfeffer",24],["Frank Smith",35],["Chelsey Franecki",35],["Reva Moore",46],["Favian Metz",38],["Lera Gutmann",12],["Kelley Klein",45]]},{"id":45,"data":[["Thurman Kuhic",48],["Ms. Nathanial Mohr",19],["Mrs. Erich Pacocha",36],["Valerie Harvey",11],["Arlo Okuneva",45],["Abel Herzog",24],["Orland Schiller",43]]},{"id":46,"data":[["Wayne Herzog DDS",17],["Margarete Hegmann",28],["Uriel Thiel",38],["Bryce Johns",31],["Mrs. Natasha Fritsch",17],["Shawn Konopelski II",32],["Litzy Purdy",27]]},{"id":47,"data":[["Everette Cole",46],["Kristin Larkin",49],["Dewayne Mitchell",37],["Anissa Ankunding",32],["Jody Strosin",37],["Kenneth Fisher",37],["Ms. Rylee Schuster",36]]},{"id":48,"data":[["Ashleigh Bahringer",27],["Ernesto Herman",13],["Griffin Reinger",16],["Lupe Koss MD",7],["Dr. Jewel Labadie",46],["Kody Wisozk",21],["Grady Wiza",44]]},{"id":49,"data":[["Billy Homenick",25],["Leonora Paucek",45],["Rubye Osinski",41],["Vern Larson",8],["Wendell Zieme",29],["Ericka Bauch",36],["Lauryn Towne",19]]},{"id":50,"data":[["Astrid Ondricka",31],["Teagan Streich",8],["Ms. Ottis Champlin",22],["Eldora Kemmer",38],["Miss Aubree Harris",12],["Jedediah Gottlieb",31],["Ardella Considine Sr.",46]]},{"id":51,"data":[["Kamryn Collier",35],["Miss Dixie Sauer",31],["Remington Schoen Sr.",8],["Garrison Reynolds",48],["Dr. Lina Wehner",14],["Kamren Ebert MD",24],["Sarah Jacobi",46]]},{"id":52,"data":[["Walker Hermann",45],["Oswaldo Wiegand Sr.",30],["Elissa McKenzie",27],["Zachary Streich",17],["Violet Ledner",50],["Alvera Pollich",31],["Ora Thiel",8]]},{"id":53,"data":[["Nicholaus Sawayn",7],["Davonte Green",17],["Mrs. Olga Legros",40],["Alia Larkin",36],["Eileen O'Kon",30],["Filomena Pacocha",26],["Mr. Gwendolyn Sipes",42]]},{"id":54,"data":[["Dayton Price",20],["Lela Mraz",22],["Dr. Emmie Hickle",22],["Shaina Wiza",28],["Jean Block IV",23],["Josue McCullough",11],["Tremaine Nader",41]]},{"id":55,"data":[["Garrison Ebert",13],["Melisa Fadel",10],["Kamron Funk II",33],["Mrs. Alvera Armstrong",42],["Jaiden Barton",42],["Fernando Hayes",6],["Mary Koss",35]]},{"id":56,"data":[["Johnnie Kuphal",25],["Holden Sipes",30],["Sean Jenkins",46],["Arturo Hermann",45],["Shayne Wehner",25],["Alba Sporer",48],["Velma Mosciski",25]]},{"id":57,"data":[["Michel Eichmann",37],["Ms. Cristopher Paucek",10],["Junior Yost",23],["Lesly Adams",11],["Wilhelmine Stiedemann",22],["Nick Ortiz",12],["Dulce Grant",31]]},{"id":58,"data":[["Margaretta Homenick",48],["Ms. Imogene Conroy",8],["Marilou Reichert DVM",27],["Albertha Becker",20],["Abe Jones Sr.",13],["Lourdes Schmitt",41],["Meagan Treutel",30]]},{"id":59,"data":[["Treva Pollich",24],["Trevor Kozey",31],["Travon Greenholt",34],["Ms. Chasity Pfeffer",45],["Minerva Cummerata",31],["Tierra Bashirian",23],["Rey Osinski I",11]]},{"id":60,"data":[["Hillary Mohr",16],["Bernadette Gottlieb",37],["Dorian Lemke",7],["Kathlyn Johns IV",35],["Alex Tillman V",30],["Taurean Lueilwitz DDS",25],["Berta Nitzsche III",13]]},{"id":61,"data":[["Dr. Audra Walsh",34],["Karen Abernathy",17],["Esperanza Bernhard",41],["Julio DuBuque",7],["Uriah Little",10],["Seamus Miller",32],["Kelsie Raynor",45]]},{"id":62,"data":[["Scarlett Mertz",48],["Ivory Durgan II",37],["Javier Aufderhar",15],["Justyn Oberbrunner",31],["Cleo Windler",47],["Miss Myra Eichmann",17],["Dexter Runolfsson",44]]},{"id":63,"data":[["Mr. Kiara Leannon",24],["April Pacocha",7],["Miss Rosendo Koepp",25],["Hellen Jaskolski Jr.",34],["Reina Zboncak",35],["Dr. Buford Stiedemann",26],["Malachi Runolfsson",37]]},{"id":64,"data":[["Easton Strosin",38],["Ms. Lilla Ruecker",47],["Ervin Spencer",9],["Thad Paucek",19],["Keira Koch PhD",48],["Ashlynn Runolfsdottir",18],["Johan Kozey",7]]},{"id":65,"data":[["Kaleigh O'Keefe",37],["Janessa Nicolas",27],["Andre Jaskolski",35],["Amaya Jakubowski",31],["Art Schmeler",19],["Yvonne Friesen",26],["Kamille Daniel Sr.",36]]},{"id":66,"data":[["Ms. Alycia Volkman",45],["Deontae Hahn",31],["Jamaal Cartwright",19],["Mr. Haylee Shanahan",45],["Ara Goodwin",22],["Jadyn Keebler",31],["Guido Windler Jr.",45]]},{"id":67,"data":[["Mrs. Imogene Farrell",42],["Frederik Prohaska",10],["Stephan Jones",33],["Pattie Schoen",7],["Harvey Hoppe",14],["Luz Lowe",31],["Cyrus Wisozk",21]]},{"id":68,"data":[["Cassandre Mraz",6],["Heidi Bogan MD",41],["Leland Romaguera",36],["Lilian Mraz",13],["Janice Muller I",48],["Thelma Walsh",24],["Nannie Hintz",10]]},{"id":69,"data":[["Zelma Hamill MD",50],["Rahsaan Zieme",9],["Rex McKenzie",16],["Jefferey Turner",5],["Freida Mayert",21],["Jeanette Wolf",37],["Destini Dicki",40]]},{"id":70,"data":[["Olin Christiansen",12],["Halie Rolfson",12],["Torrey Dicki",18],["Wendy Ondricka",31],["Philip Schaden",49],["Erik Bergnaum",28],["Isabelle Wiza",48]]},{"id":71,"data":[["Dr. Bernie Nicolas",35],["Felton Cartwright",48],["Colby Nicolas",50],["Lorna Carroll MD",30],["Rubye Maggio",43],["Paxton Borer",34],["Adrienne Green",19]]},{"id":72,"data":[["Koby Aufderhar",41],["Jeanie Towne",43],["Roy Leannon DVM",38],["Yvonne Parker",40],["Manuel Bogisich",38],["Adeline Jacobson",31],["Claudia Hermiston",11]]},{"id":73,"data":[["Karianne Ankunding",28],["Lulu Metz",26],["Elvie Klocko",49],["Evangeline Mraz",23],["Lukas Okuneva",13],["Mrs. Angelo Purdy",50],["Norberto Mayer",30]]},{"id":74,"data":[["Damien Little",10],["Eulalia Kreiger",12],["Baby Schowalter",49],["Shanelle Collier",44],["Gretchen Donnelly DDS",28],["Dr. Mollie Fahey",29],["Cortney Zulauf",13]]},{"id":75,"data":[["Tyreek Rodriguez",48],["Jermey Bruen",6],["Mikel Christiansen",23],["Mr. Angus Gerhold",47],["Jadyn Labadie",18],["Scottie Kunze",27],["Merlin Quigley",5]]},{"id":76,"data":[["Dr. Geoffrey Casper",21],["Adan Zieme",19],["Sanford Block",20],["Blanca Feest",17],["Trenton Daniel",20],["Lesley Orn",17],["Dr. Thad Monahan",34]]},{"id":77,"data":[["Tamia Jacobs V",16],["August Lebsack",11],["Destiney McCullough DVM",18],["Triston Farrell",18],["Delmer Zieme",22],["Ms. Reece Gerlach",8],["Rachelle Grant",24]]},{"id":78,"data":[["Trisha Miller",36],["Ettie Dibbert IV",33],["Eleanore West",5],["Miss Maia Price",28],["Earl Johns",25],["Mauricio Gusikowski",12],["Reymundo VonRueden",17]]},{"id":79,"data":[["Alvis Olson",10],["Leonor McCullough",39],["Amari Hettinger Sr.",47],["Julius Barrows",42],["Boyd Nader",50],["Joany Conroy Jr.",43],["Haven Abshire",35]]},{"id":80,"data":[["Joshua Bartell",43],["Isidro Goyette",44],["Macy Champlin",25],["Buford Hoeger Jr.",48],["Alek Stroman",47],["Lea Hirthe",39],["Marshall Pouros",37]]},{"id":81,"data":[["Aditya Yost",12],["Dulce Pollich",45],["Annalise Schmeler",19],["Laila Hauck",18],["Pearline Zieme",37],["Pearl Gleason",40],["Virgie Braun",35]]},{"id":82,"data":[["Emile Veum",17],["Magdalena Kreiger",21],["Lilliana Sawayn",7],["Mr. Aurelio Quigley",47],["Don Bauch DVM",12],["Dr. Claudie Dooley",28],["Ford Brekke",19]]},{"id":83,"data":[["Israel Schaefer",20],["Nyah Hansen",17],["Baron Gutmann",7],["Dereck Rath",34],["Shawn Stanton I",37],["Sibyl Labadie",41],["Conrad Tremblay",37]]},{"id":84,"data":[["Florian Champlin",37],["Darrin Senger",20],["Curt Crona DVM",43],["Sherwood Treutel",48],["Jess Leannon",10],["Gino Watsica",23],["Bernice Rowe",25]]},{"id":85,"data":[["Lexie Ryan IV",36],["Alejandrin Mosciski",16],["Hazle Shields",16],["Mr. Leann Bahringer",19],["Arch Labadie I",23],["Eugene Gibson",37],["Domenico Sanford",12]]},{"id":86,"data":[["Jeffrey Purdy",17],["Monserrat Reynolds",6],["Wade Cremin",21],["Makayla Krajcik",12],["Desmond Price",11],["Dovie Swift",23],["Bart Ullrich",28]]},{"id":87,"data":[["Dr. Stevie Rogahn",26],["Anjali Hirthe IV",35],["Koby Koepp",16],["Miss Hanna Flatley",43],["Marlene Oberbrunner",7],["Jerad Shields",31],["Shayna Walter III",14]]},{"id":88,"data":[["Billie Stamm",50],["Tamia Legros",9],["Leonel Bernhard",40],["Wilmer Kiehn",36],["Rashad Schneider V",38],["Julien Stark",7],["Isabell Farrell",17]]},{"id":89,"data":[["Ericka Gutkowski Jr.",44],["Nichole Cassin",35],["Lyla Borer",13],["Michale VonRueden",20],["Aurore Frami",7],["Madie Stoltenberg",8],["Lisandro Pfannerstill DVM",38]]},{"id":90,"data":[["Ardella Torphy",36],["Van Hermann",47],["Mckenzie Kilback",28],["Savannah Huels",42],["Kayleigh Bernier",49],["Miss Thora Bashirian",19],["Vena Volkman",30]]},{"id":91,"data":[["Celine Turcotte",44],["Ressie King",19],["Jose Kozey",6],["Cicero Parker",34],["Lacey Smitham II",49],["Yessenia Reinger",47],["Alayna Funk",40]]},{"id":92,"data":[["Aron Satterfield",7],["Merl Lemke",47],["Ora Zboncak",17],["Alize Botsford",5],["Gerald Watsica IV",20],["Rosalinda Carroll",6],["Alda Swaniawski",18]]},{"id":93,"data":[["Shakira Stoltenberg",29],["Nathanial Kuhn",49],["Mr. Sophie Weissnat",30],["Anthony Dach",33],["Kaylee Frami",33],["Abelardo Tillman",14],["Gerry Kiehn",5]]},{"id":94,"data":[["Keanu Aufderhar",11],["Samson Boyle",36],["Dandre Dach",43],["Jarvis Windler",42],["Adaline Torp",12],["Ms. Myra Goldner",21],["Olga Conn",38]]},{"id":95,"data":[["Clinton Farrell",15],["Jaylon Ebert",39],["Viviane Harber",39],["Cecilia Smitham",45],["Alvera Ebert",36],["Mrs. Carmelo Hagenes",6],["Raquel Bogisich",5]]},{"id":96,"data":[["Gene Grady",19],["Khalid Heathcote",38],["Meda Herman",30],["Enoch Littel",6],["Demond Parker",12],["Juana Gibson",48],["Amaya Larkin IV",43]]},{"id":97,"data":[["Augustine Waters",17],["Beverly Vandervort",14],["Ernest Dickens",31],["Isaiah Kris",33],["Miss Aryanna Wolff",45],["Lenny Olson",45],["Darrell Purdy",34]]},{"id":98,"data":[["Sadye Goyette",47],["Rafael Vandervort",12],["Armando Watsica",27],["Christopher McDermott",12],["Lessie Barton",26],["Mr. Braden Aufderhar",32],["Bradley Schmitt",14]]},{"id":99,"data":[["Mrs. Nakia D'Amore",18],["Carleton Corkery DDS",14],["Liliane Raynor",24],["Keanu Kuvalis",50],["Miss Arnold Stoltenberg",6],["Yasmine Kautzer",17],["Mylene Kertzmann",24]]},{"id":100,"data":[["Rosa Nikolaus Sr.",40],["Anissa Funk",18],["Lance Batz",13],["Lawson O'Hara",20],["Leland Davis",34],["Cierra Pfeffer",48],["Madelynn Schamberger",43]]}]}}